{
    "$schema": "https://json-schema.org/draft/2020-12/schema",
    "$id": "https://example.com/crystal.schema.json",
    "title": "Crystal",
    "description": "Crystal",
    "type": "object",
    "properties": {
        "name": {
            "type": "string",
            "description": "The name of the crystal."
        },
        "material": {
            "type": "string",
            "description": "The material of the crystal."
        },
        "face": {
            "type": "string",
            "description": "The face of the crystal."
        },
        "samplePlate": {
            "type": "string",
            "description": "Sample plate of the crystal."
        },
        "diameter": {
            "type": "object",
            "description": "Diameter of the crystal.",
            "properties": {
                "value": {
                    "type": "number"
                },
                "unit": {
                    "type": "string"
                }
            }
        },
        "height": {
            "type": "object",
            "description": "Height of the crystal.",
            "properties": {
                "value": {
                    "type": "number"
                },
                "unit": {
                    "type": "string"
                }
            }
        },
        "hazardous": {
            "type": "boolean",
            "description": "Whether the crystal is dangerous."
        },
        "hazardousSpecification": {
            "type": "string",
            "description": "The specification of the type of danger."
        },
        "fridge": {
            "type": "boolean",
            "description": "Whether the crystal must be stored in a fridge."
        },
        "noLight": {
            "type": "boolean",
            "description": "Whether the crystal must be stored in darkness."
        },
        "dry": {
            "type": "boolean",
            "description": "Whether the crystal must be stored in a dry environment."
        },
        "noOxygen": {
            "type": "boolean",
            "description": "Whether the crystal must be stored in an anaerobic environment."
        },
        "otherStorageCondition": {
            "type": "boolean",
            "description": "Whether the crystal must be stored following another special storage condition."
        },
        "otherStorageConditionSpecification": {
            "type": "string",
            "description": "The specification of the other special storage condition."
        },
        "specifications": {
            "type": "string",
            "description": "Specifications of the crystal."
        },
        "receiveDate": {
            "type": "string",
            "description": "Date when the crystal was received.",
            "format": "date"
        },
        "referenceNumber": {
            "type": "string",
            "description": "Reference number of the crystal."
        },
        "comments": {
            "type": "string",
            "description": "Comments to the wafer substrate."
        },
        "storage": {
            "$ref": "./storage.schema.json"
        },
        "chemist": {
            "$ref": "./supplier.schema.json"
        },
        "required": ["name", "material", "face"]
    }
}